pytest_oduit.py
pytest_oduit-0.3.1.dist-info/licenses/LICENSE
pytest_oduit-0.3.1.dist-info/METADATA
pytest_oduit-0.3.1.dist-info/WHEEL
pytest_oduit-0.3.1.dist-info/entry_points.txt
pytest_oduit-0.3.1.dist-info/top_level.txt
pytest_oduit-0.3.1.dist-info/RECORD
