Metadata-Version: 2.4
Name: pytest-oduit
Version: 0.3.1
Summary: py.test plugin to run Odoo tests
Author-email: Holger Nahrstaedt <holger.nahrstaedt@hasomed.de>
License: AGPLv3
Project-URL: Homepage, https://github.com/oduit/pytest-oduit
Platform: any
Classifier: Development Status :: 5 - Production/Stable
Classifier: Intended Audience :: Developers
Classifier: License :: OSI Approved :: GNU Affero General Public License v3
Classifier: Operating System :: POSIX
Classifier: Topic :: Software Development :: Testing
Classifier: Topic :: Software Development :: Libraries
Classifier: Topic :: Utilities
Classifier: Programming Language :: Python :: 3.9
Classifier: Programming Language :: Python :: 3.10
Classifier: Programming Language :: Python :: 3.11
Classifier: Programming Language :: Python :: 3.12
Classifier: Programming Language :: Python :: 3.13
Requires-Python: >=3.9
License-File: LICENSE
Requires-Dist: pytest>=8
Requires-Dist: oduit
Dynamic: license-file
